speedpix/__init__.py
speedpix/client.py
speedpix/exceptions.py
speedpix/file.py
speedpix/helpers.py
speedpix/prediction.py
speedpix/py.typed
speedpix/resource.py
speedpix/schema.py
speedpix-1.0.4.dist-info/licenses/LICENSE
speedpix-1.0.4.dist-info/METADATA
speedpix-1.0.4.dist-info/WHEEL
speedpix-1.0.4.dist-info/top_level.txt
speedpix-1.0.4.dist-info/RECORD
