Metadata-Version: 2.4
Name: speedpix
Version: 1.0.4
Summary: 智作工坊 Python SDK
Author: Aliyun, Inc.
License-Expression: MIT
Project-URL: homepage, https://eduplatform-sp.console.aliyun.com/
Project-URL: repository, https://github.com/aliyun/speedpix-python
Requires-Python: >=3.8
License-File: LICENSE
Requires-Dist: httpx<1,>=0.21.0
Requires-Dist: packaging
Requires-Dist: pydantic>1.10.7
Requires-Dist: typing_extensions>=4.5.0
Requires-Dist: requests>=2.25.0
Requires-Dist: dataclass_wizard>=0.35.0
Requires-Dist: aiofiles>=0.8.0
Dynamic: license-file
